PyGraphDFS/__init__.py
PyGraphDFS/graph.py
PyGraphDFS-0.1.dist-info/LICENSE.txt
PyGraphDFS-0.1.dist-info/METADATA
PyGraphDFS-0.1.dist-info/WHEEL
PyGraphDFS-0.1.dist-info/top_level.txt
PyGraphDFS-0.1.dist-info/RECORD
